{"park": "Mount Rainer", "months": 36, "forecast": [{"Year": 2025, "Month": 11, "predicted_visits": 36124.11, "crowd_level": "low", "low_threshold": 39529.8, "high_threshold": 153405.59999999998}, {"Year": 2025, "Month": 12, "predicted_visits": 21440.055, "crowd_level": "low", "low_threshold": 39529.8, "high_threshold": 153405.59999999998}, {"Year": 2026, "Month": 1, "predicted_visits": 28401.81, "crowd_level": "low", "low_threshold": 39529.8, "high_threshold": 153405.59999999998}, {"Year": 2026, "Month": 2, "predicted_visits": 24568.88, "crowd_level": "low", "low_threshold": 39529.8, "high_threshold": 153405.59999999998}, {"Year": 2026, "Month": 3, "predicted_visits": 25189.355, "crowd_level": "low", "low_threshold": 39529.8, "high_threshold": 153405.59999999998}, {"Year": 2026, "Month": 4, "predicted_visits": 45439.805, "crowd_level": "medium", "low_threshold": 39529.8, "high_threshold": 153405.59999999998}, {"Year": 2026, "Month": 5, "predicted_visits": 109191.945, "crowd_level": "medium", "low_threshold": 39529.8, "high_threshold": 153405.59999999998}, {"Year": 2026, "Month": 6, "predicted_visits": 246557.35, "crowd_level": "high", "low_threshold": 39529.8, "high_threshold": 153405.59999999998}, {"Year": 2026, "Month": 7, "predicted_visits": 363743.535, "crowd_level": "high", "low_threshold": 39529.8, "high_threshold": 153405.59999999998}, {"Year": 2026, "Month": 8, "predicted_visits": 407078.85, "crowd_level": "high", "low_threshold": 39529.8, "high_threshold": 153405.59999999998}, {"Year": 2026, "Month": 9, "predicted_visits": 187944.69, "crowd_level": "high", "low_threshold": 39529.8, "high_threshold": 153405.59999999998}, {"Year": 2026, "Month": 10, "predicted_visits": 113051.165, "crowd_level": "medium", "low_threshold": 39529.8, "high_threshold": 153405.59999999998}, {"Year": 2026, "Month": 11, "predicted_visits": 44808.45, "crowd_level": "medium", "low_threshold": 39529.8, "high_threshold": 153405.59999999998}, {"Year": 2026, "Month": 12, "predicted_visits": 27108.945, "crowd_level": "low", "low_threshold": 39529.8, "high_threshold": 153405.59999999998}, {"Year": 2027, "Month": 1, "predicted_visits": 29148.275, "crowd_level": "low", "low_threshold": 39529.8, "high_threshold": 153405.59999999998}, {"Year": 2027, "Month": 2, "predicted_visits": 28195.18, "crowd_level": "low", "low_threshold": 39529.8, "high_threshold": 153405.59999999998}, {"Year": 2027, "Month": 3, "predicted_visits": 26813.02, "crowd_level": "low", "low_threshold": 39529.8, "high_threshold": 153405.59999999998}, {"Year": 2027, "Month": 4, "predicted_visits": 44393.75, "crowd_level": "medium", "low_threshold": 39529.8, "high_threshold": 153405.59999999998}, {"Year": 2027, "Month": 5, "predicted_visits": 141265.865, "crowd_level": "medium", "low_threshold": 39529.8, "high_threshold": 153405.59999999998}, {"Year": 2027, "Month": 6, "predicted_visits": 256946.105, "crowd_level": "high", "low_threshold": 39529.8, "high_threshold": 153405.59999999998}, {"Year": 2027, "Month": 7, "predicted_visits": 365967.03, "crowd_level": "high", "low_threshold": 39529.8, "high_threshold": 153405.59999999998}, {"Year": 2027, "Month": 8, "predicted_visits": 400814.7, "crowd_level": "high", "low_threshold": 39529.8, "high_threshold": 153405.59999999998}, {"Year": 2027, "Month": 9, "predicted_visits": 188934.055, "crowd_level": "high", "low_threshold": 39529.8, "high_threshold": 153405.59999999998}, {"Year": 2027, "Month": 10, "predicted_visits": 115654.66, "crowd_level": "medium", "low_threshold": 39529.8, "high_threshold": 153405.59999999998}, {"Year": 2027, "Month": 11, "predicted_visits": 56286.38, "crowd_level": "medium", "low_threshold": 39529.8, "high_threshold": 153405.59999999998}, {"Year": 2027, "Month": 12, "predicted_visits": 32198.87, "crowd_level": "low", "low_threshold": 39529.8, "high_threshold": 153405.59999999998}, {"Year": 2028, "Month": 1, "predicted_visits": 32240.32, "crowd_level": "low", "low_threshold": 39529.8, "high_threshold": 153405.59999999998}, {"Year": 2028, "Month": 2, "predicted_visits": 30699.92, "crowd_level": "low", "low_threshold": 39529.8, "high_threshold": 153405.59999999998}, {"Year": 2028, "Month": 3, "predicted_visits": 27063.28, "crowd_level": "low", "low_threshold": 39529.8, "high_threshold": 153405.59999999998}, {"Year": 2028, "Month": 4, "predicted_visits": 43454.07, "crowd_level": "medium", "low_threshold": 39529.8, "high_threshold": 153405.59999999998}, {"Year": 2028, "Month": 5, "predicted_visits": 148441.565, "crowd_level": "medium", "low_threshold": 39529.8, "high_threshold": 153405.59999999998}, {"Year": 2028, "Month": 6, "predicted_visits": 260193.225, "crowd_level": "high", "low_threshold": 39529.8, "high_threshold": 153405.59999999998}, {"Year": 2028, "Month": 7, "predicted_visits": 365114.53, "crowd_level": "high", "low_threshold": 39529.8, "high_threshold": 153405.59999999998}, {"Year": 2028, "Month": 8, "predicted_visits": 400234.92, "crowd_level": "high", "low_threshold": 39529.8, "high_threshold": 153405.59999999998}, {"Year": 2028, "Month": 9, "predicted_visits": 190095.83, "crowd_level": "high", "low_threshold": 39529.8, "high_threshold": 153405.59999999998}, {"Year": 2028, "Month": 10, "predicted_visits": 116633.2, "crowd_level": "medium", "low_threshold": 39529.8, "high_threshold": 153405.59999999998}]}